hubugs/__init__.py
hubugs/_version.py
hubugs/models.py
hubugs/template.py
hubugs/utils.py
hubugs/locale/hubugs.pot
hubugs/templates/default/edit/default.mkd
hubugs/templates/default/edit/hubugs_report.mkd
hubugs/templates/default/edit/open.mkd
hubugs/templates/default/view/issue.txt
hubugs/templates/default/view/list.txt
hubugs/templates/default/view/list_milestones.txt
hubugs/templates/default/view/theme.txt
hubugs-0.19.0.dist-info/COPYING
hubugs-0.19.0.dist-info/METADATA
hubugs-0.19.0.dist-info/WHEEL
hubugs-0.19.0.dist-info/entry_points.txt
hubugs-0.19.0.dist-info/top_level.txt
hubugs-0.19.0.dist-info/RECORD
