Metadata-Version: 2.1
Name: hubugs
Version: 0.19.0
Summary: Simple client for GitHub issues
Home-page: https://github.com/JNRowe/hubugs
Author: James Rowe
Author-email: jnrowe@gmail.com
License: GPL-3
Keywords: github bugs cli'
Platform: UNKNOWN
Classifier: Development Status :: 5 - Production/Stable
Classifier: Environment :: Console
Classifier: Intended Audience :: Developers
Classifier: Intended Audience :: End Users/Desktop
Classifier: License :: OSI Approved
Classifier: License :: OSI Approved :: GNU General Public License (GPL)
Classifier: License :: OSI Approved :: GNU General Public License v3 or later (GPLv3+)
Classifier: Natural Language :: English
Classifier: Operating System :: OS Independent
Classifier: Programming Language :: Python
Classifier: Programming Language :: Python :: 3
Classifier: Programming Language :: Python :: 3.5
Classifier: Programming Language :: Python :: 3.6
Classifier: Programming Language :: Python :: 3.7
Classifier: Topic :: Communications
Classifier: Topic :: Internet
Classifier: Topic :: Software Development
Classifier: Topic :: Software Development :: Bug Tracking
Classifier: Topic :: Utilities
Requires-Dist: click (>=6.2)
Requires-Dist: html2text
Requires-Dist: Jinja2 (>=2)
Requires-Dist: jnrbase[iso_8601,colour,net] (>=v1.1.1)
Requires-Dist: misaka (>=1.0.2)
Requires-Dist: Pygments
